forecastcards/__init__.py
forecastcards/cardset.py
forecastcards/dataset.py
forecastcards/project.py
forecastcards/schema.py
forecastcards/util.py
forecastcards/examples/.DS_Store
forecastcards/examples/ecdot-lu123-munchkin_tod/poi.csv
forecastcards/examples/ecdot-lu123-munchkin_tod/project.csv
forecastcards/examples/ecdot-lu123-munchkin_tod/scenarios.csv
forecastcards/examples/ecdot-lu123-munchkin_tod/forecasts/forecast-A1-1960-1940-F1.csv
forecastcards/examples/ecdot-lu123-munchkin_tod/observations/.DS_Store
forecastcards/examples/ecdot-lu123-munchkin_tod/observations/observations-2015.csv
forecastcards/examples/ecdot-rx123-ybr_hov/poi.csv
forecastcards/examples/ecdot-rx123-ybr_hov/project.csv
forecastcards/examples/ecdot-rx123-ybr_hov/scenarios.csv
forecastcards/examples/ecdot-rx123-ybr_hov/forecasts/forecast-A1-1960-1940-F1.csv
forecastcards/examples/ecdot-rx123-ybr_hov/observations/observations-1935.csv
forecastcards/examples/ecdot-rx123-ybr_hov/observations/observations-1960.csv
forecastcards/notebooks/.DS_Store
forecastcards/notebooks/Create_Forecast_Cards.ipynb
forecastcards/notebooks/Data_Validation_and_Preparation.ipynb
forecastcards/notebooks/Estimate_Quantiles.ipynb
forecastcards/notebooks/Explore_Data_Schemas.ipynb
forecastcards/notebooks/.ipynb_checkpoints/Data_Validation_and_Preparation-Local-checkpoint.ipynb
forecastcards/notebooks/.ipynb_checkpoints/Data_Validation_and_Preparation-checkpoint.ipynb
forecastcards/scripts/validate_cardset.py
forecastcards/scripts/validate_project.py
forecastcards-0.1.dev1.data/scripts/validate_cardset.py
forecastcards-0.1.dev1.data/scripts/validate_project.py
forecastcards-0.1.dev1.dist-info/LICENSE.txt
forecastcards-0.1.dev1.dist-info/METADATA
forecastcards-0.1.dev1.dist-info/WHEEL
forecastcards-0.1.dev1.dist-info/top_level.txt
forecastcards-0.1.dev1.dist-info/RECORD
