Metadata-Version: 2.1
Name: forecastcards
Version: 0.1.dev1
Summary: UNKNOWN
Home-page: https://github.com/e-lo/forecastcards
Author: Elizabeth Sall
Author-email: easall@gmail.com
License: UNKNOWN
Platform: UNKNOWN
Classifier: Programming Language :: Python :: 3
Classifier: License :: OSI Approved :: Apache Software License
Classifier: Operating System :: OS Independent
Classifier: Development Status :: 3 - Alpha
Requires-Dist: pandas (==0.22)
Requires-Dist: requests
Requires-Dist: goodtables
Requires-Dist: tableschema
Requires-Dist: graphviz
Requires-Dist: statsmodels
Requires-Dist: jupyter
